cli/__init__.py
cli/config.py
cli/main.py
cli/cloud/__init__.py
cli/cloud/compiler.py
cli/cloud/stack.py
cli/cloud/aws/__init__.py
cli/cloud/aws/build.py
cli/cloud/aws/compiler.py
cli/cloud/aws/stack.py
cli/cloud/aws/status.py
cli/cloud/aws/validate.py
cli/cloud/gcp/__init__.py
cli/cloud/gcp/build.py
cli/cloud/gcp/stack.py
cli/cloud/gcp/validate.py
cli/modules/__init__.py
cli/modules/cleanup.py
cli/modules/create.py
cli/modules/deploy.py
cli/modules/show.py
cli/modules/utils.py
cli/templates/__init__.py
cli/templates/core.py
cli/templates/initialize.py
cli/templates/project.py
cli/templates/repository.py
cli/templates/service.py
cli/templates/subscription.py
freeldep/__init__.py
freeldep/config.py
freeldep/main.py
freeldep/cloud/__init__.py
freeldep/cloud/compiler.py
freeldep/cloud/stack.py
freeldep/cloud/aws/__init__.py
freeldep/cloud/aws/build.py
freeldep/cloud/aws/stack.py
freeldep/cloud/aws/status.py
freeldep/cloud/aws/validate.py
freeldep/cloud/gcp/__init__.py
freeldep/cloud/gcp/build.py
freeldep/cloud/gcp/stack.py
freeldep/cloud/gcp/validate.py
freeldep/modules/__init__.py
freeldep/modules/cleanup.py
freeldep/modules/create.py
freeldep/modules/deploy.py
freeldep/modules/show.py
freeldep/modules/utils.py
freeldep/templates/__init__.py
freeldep/templates/core.py
freeldep/templates/initialize.py
freeldep/templates/project.py
freeldep/templates/repository.py
freeldep/templates/service.py
freeldep/templates/subscription.py
templates/__init__.py
templates/aws/__init__.py
templates/aws/deployer-core.yaml
templates/aws/deployer-initialize.yaml
templates/aws/deployer-project.yaml
templates/aws/deployer-repository.yaml
templates/aws/deployer-service.yaml
templates/aws/deployer-subscription.yaml
templates/gcp/__init__.py
templates/gcp/deployer-initialize.yaml
tests/__init__.py
tests/integration/__init__.py
tests/integration/test_cli.py
tests/integration/test_cli_errors.py
tests/unit/__init__.py
tests/unit/test_config.py
tests/unit/test_main.py
freeldep-0.7.3.dist-info/LICENSE
freeldep-0.7.3.dist-info/METADATA
freeldep-0.7.3.dist-info/WHEEL
freeldep-0.7.3.dist-info/entry_points.txt
freeldep-0.7.3.dist-info/namespace_packages.txt
freeldep-0.7.3.dist-info/top_level.txt
freeldep-0.7.3.dist-info/RECORD
