Metadata-Version: 2.1
Name: freeldep
Version: 0.7.3
Summary: Serverless Infrastructure as code deployment
Home-page: https://github.com/MatthieuBlais/freeldep
Author: Matthieu Blais
Author-email: matthieu@freeldom.com
License: UNKNOWN
Download-URL: https://github.com/MatthieuBlais/freeldep.git
Platform: Any
Classifier: Development Status :: 3 - Alpha
Classifier: License :: OSI Approved :: Apache Software License
Classifier: Programming Language :: Python
Classifier: Programming Language :: Python :: 3.8
Classifier: Intended Audience :: Developers
Classifier: Environment :: Console
Requires-Dist: Click (==7.1.2)
Requires-Dist: jinja2 (==2.11.2)
Requires-Dist: pyaml (==20.4.0)
Requires-Dist: cfn-lint (==0.44.1)
Requires-Dist: google-cloud-storage (==1.35.0)
